pix_plus/__init__.py
pix_plus/protos/__init__.py
pix_plus/protos/proto_pixplus_pb2.py
pix_plus/service_packages/__init__.py
pix_plus/service_packages/_version.py
pix_plus/service_packages/logger.py
pix_plus/service_packages/shared.py
pix_plus-1.0.4.dist-info/LICENSE
pix_plus-1.0.4.dist-info/METADATA
pix_plus-1.0.4.dist-info/WHEEL
pix_plus-1.0.4.dist-info/top_level.txt
pix_plus-1.0.4.dist-info/RECORD
