Metadata-Version: 2.1
Name: pix_plus
Version: 1.0.4
Summary: A package for Pix+ services, which contain proto types
Home-page: https://github.com/pypa/pix_plus
Author: Udini.co
Author-email: dimaprokopp@gmail.com
Project-URL: Bug Tracker, https://github.com/pypa/pix_plus/issues
Classifier: Programming Language :: Python :: 3
Classifier: License :: OSI Approved :: MIT License
Classifier: Operating System :: OS Independent
Requires-Python: >=3.8
License-File: LICENSE
